README.rst
setup.cfg
setup.py
./__init__.py
./account.py
./account.xml
./invoice.py
./invoice.xml
./report_html_accounts.py
./report_html_accounts.xml
./tryton.cfg
./reports/aged_balance.html
./reports/base.html
./reports/invoice.html
./reports/multi-record-base.html
./reports/party_account_statement.html
./reports/css/bootstrap/css/bootstrap.min.css
./reports/css/bootstrap/fonts/glyphicons-halflings-regular.eot
./reports/css/bootstrap/fonts/glyphicons-halflings-regular.svg
./reports/css/bootstrap/fonts/glyphicons-halflings-regular.ttf
./reports/css/bootstrap/fonts/glyphicons-halflings-regular.woff
./reports/css/bootstrap/fonts/glyphicons-halflings-regular.woff2
./reports/css/font-awesome/css/font-awesome.min.css
./tests/__init__.py
./tests/test_base.py
./tests/test_invoice.py
./tests/test_party.py
./tests/test_views_depends.py
./view/report_party_account_statement_form.xml
fio_report_html_accounts.egg-info/PKG-INFO
fio_report_html_accounts.egg-info/SOURCES.txt
fio_report_html_accounts.egg-info/dependency_links.txt
fio_report_html_accounts.egg-info/entry_points.txt
fio_report_html_accounts.egg-info/not-zip-safe
fio_report_html_accounts.egg-info/requires.txt
fio_report_html_accounts.egg-info/top_level.txt